solpoc/__init__.py
solpoc/cli.py
solpoc/functions_SolPOC.py
solpoc/readme.md
solpoc/Materials/Ag.txt
solpoc/Materials/Ag_Babar.txt
solpoc/Materials/Ag_Hagemann.txt
solpoc/Materials/Ag_McPeak.txt
solpoc/Materials/Ag_RBB.txt
solpoc/Materials/Ag_RLD.txt
solpoc/Materials/Ag_Rakic.txt
solpoc/Materials/Ag_W.txt
solpoc/Materials/Al.txt
solpoc/Materials/Al2O3.txt
solpoc/Materials/Al2O3_K.txt
solpoc/Materials/AlN.txt
solpoc/Materials/Al_Hagemann.txt
solpoc/Materials/Al_McPeak.txt
solpoc/Materials/Al_Orda.txt
solpoc/Materials/Al_RBB.txt
solpoc/Materials/Al_RLD.txt
solpoc/Materials/Al_Rakic.txt
solpoc/Materials/Au.txt
solpoc/Materials/Au_RLD.txt
solpoc/Materials/BK10.txt
solpoc/Materials/BK7.txt
solpoc/Materials/BK7_T.txt
solpoc/Materials/BaF51.txt
solpoc/Materials/BaK1.txt
solpoc/Materials/BaK2.txt
solpoc/Materials/BaK4.txt
solpoc/Materials/BaK4N.txt
solpoc/Materials/BaLF4N.txt
solpoc/Materials/BaSF2.txt
solpoc/Materials/BalF4.txt
solpoc/Materials/CaF2.txt
solpoc/Materials/Ch_Rakic.txt
solpoc/Materials/Co.txt
solpoc/Materials/Cr.txt
solpoc/Materials/Cr2O3_COM.txt
solpoc/Materials/Cr_RLD.txt
solpoc/Materials/Cu.txt
solpoc/Materials/F2.txt
solpoc/Materials/F5.txt
solpoc/Materials/FK51A.txt
solpoc/Materials/Fe.txt
solpoc/Materials/GaAs.txt
solpoc/Materials/Human_eye.txt
solpoc/Materials/ITO.txt
solpoc/Materials/K10.txt
solpoc/Materials/K10N.txt
solpoc/Materials/K7.txt
solpoc/Materials/K7N.txt
solpoc/Materials/KF9.txt
solpoc/Materials/KF9N.txt
solpoc/Materials/LF5.txt
solpoc/Materials/LLF1.txt
solpoc/Materials/LaF2.txt
solpoc/Materials/LaF35.txt
solpoc/Materials/LaK14.txt
solpoc/Materials/LaK21.txt
solpoc/Materials/LaK34.txt
solpoc/Materials/LaK7.txt
solpoc/Materials/LaSF.txt
solpoc/Materials/LaSF9N.txt
solpoc/Materials/MgF2.txt
solpoc/Materials/MgO.txt
solpoc/Materials/Mo.txt
solpoc/Materials/Ni.txt
solpoc/Materials/NiRakic.txt
solpoc/Materials/PC.txt
solpoc/Materials/PK52A.txt
solpoc/Materials/PSK3.txt
solpoc/Materials/PSK3N.txt
solpoc/Materials/PSK53A.txt
solpoc-0.9.7.dist-info/licenses/LICENSE
solpoc-0.9.7.dist-info/METADATA
solpoc-0.9.7.dist-info/WHEEL
solpoc-0.9.7.dist-info/entry_points.txt
solpoc-0.9.7.dist-info/top_level.txt
solpoc-0.9.7.dist-info/RECORD
