Metadata-Version: 2.4
Name: solpoc
Version: 0.9.7
Summary: Solar Performances Optimization Code (SolPOC) is an Academic research code, used for solar energy. SolPOC can solve and optimize a stack of thin layers for designed solar mirror, anti-reflective coating, thermal absorber etc.
Author-email: Antoine Grosjean <antoine.grosjean@epf.fr>, Audrey Soum-Glaude <Audrey.Soum-Glaude@promes.cnrs.fr>, Antoine Moreau <antoine.moreau@uca.fr>, Pauline Bennet <pauline.bennet.pro@gmail.com>, Thalita Drumond <thalita.drumond@epf.fr>
Maintainer-email: Thalita Drumond <thalita.drumond@epf.fr>, Antoine Grosjean <antoine.grosjean@epf.fr>
Project-URL: Homepage, https://github.com/SolPOCandCo/SolPOC
Project-URL: Issues, https://github.com/SolPOCandCo/SolPOC/issues
Keywords: SolPOC,thin layers stack,multilayer coating,global optimization,solar energy,optics
Classifier: Programming Language :: Python :: 3
Classifier: Operating System :: OS Independent
Requires-Python: >=3.9
License-File: LICENSE
Requires-Dist: numpy
Requires-Dist: scipy
Requires-Dist: matplotlib
Requires-Dist: jupyter
Requires-Dist: solcore>=5.10.0
Dynamic: license-file
